aiovkrmq/__init__.py
aiovkrmq/api.py
aiovkrmq/exceptions.py
aiovkrmq/session.py
aiovkrmq/utils.py
aiovkrmq-1.1.0.dist-info/METADATA
aiovkrmq-1.1.0.dist-info/WHEEL
aiovkrmq-1.1.0.dist-info/top_level.txt
aiovkrmq-1.1.0.dist-info/RECORD
