Metadata-Version: 2.1
Name: aiovkrmq
Version: 1.1.0
Summary: An async library to work with vkAPIService. Useless if you don't have the service.
Home-page: https://gitlab.com/gladbot/aiovkrmq
Author: Mikhail Migushov
Author-email: me@chuvash.pw
License: UNKNOWN
Platform: UNKNOWN
Classifier: Programming Language :: Python :: 3.7
Requires-Dist: aioamqp
